NeoTopology-1.0.2.data/scripts/fixpdb.py
ttk/Topology.py
ttk/__init__.py
ttk/calculator/__init__.py
ttk/calculator/aligned_rmsd.py
ttk/calculator/dimer.py
ttk/core/Atom.py
ttk/core/Bond.py
ttk/core/Chain.py
ttk/core/Element.py
ttk/core/Entity.py
ttk/core/Residue.py
ttk/core/UnitCell.py
ttk/core/__init__.py
ttk/core/utils.py
ttk/data/__init__.py
ttk/io/PDBFile.py
ttk/io/PDBUtil.py
ttk/io/PDBxParser.py
ttk/io/__init__.py
ttk/io/align.py
ttk/io/residue_export.py
ttk/io/topology_export.py
ttk/io/topology_parser.py
ttk/io/visualize.py
ttk/math/Rotation.py
ttk/math/__init__.py
ttk/math/vector.py
ttk/utils/__init__.py
ttk/utils/sequence.py
NeoTopology-1.0.2.dist-info/METADATA
NeoTopology-1.0.2.dist-info/WHEEL
NeoTopology-1.0.2.dist-info/top_level.txt
NeoTopology-1.0.2.dist-info/RECORD
