Metadata-Version: 2.1
Name: NeoTopology
Version: 1.0.2
Author: huyilang
Project-URL: Homepage, https://github.com/NeoBinder/NeoTopology
Project-URL: Issues, https://github.com/NeoBinder/NeoTopology/issues
Classifier: Programming Language :: Python :: 3
Classifier: License :: OSI Approved :: MIT License
Classifier: Operating System :: OS Independent
Requires-Python: >=3.7
